[{"code": "02667", "name": "同仁堂医养", "type": "inst", "price": "5.48-6.21", "lot": 500, "fee": 2768, "subStart": "2026-06-26", "subEnd": "2026-07-02", "listDate": "2026-07-07", "cornerstone": "3家/47%", "cs": 4, "hot": "⚪偏低", "hs": 1, "mcap": "~27亿", "gs": true, "sponsor": "中金", "loc": "北京", "sh": "同仁堂集团84%", "gain": "+10~25%", "dec": "适度·一手", "note": "降价25%重招·Aurora基石削减", "pubLots": 21631, "interest": 1, "mech": "B机制", "margin": "18x", "jiaTiers": [30, 70, 140, 200, 400, 600, 1000, 1400, 1800], "yiTiers": [], "allLots": [{"lots": 1, "amt": 3136.31}, {"lots": 2, "amt": 6272.63}, {"lots": 3, "amt": 9408.94}, {"lots": 4, "amt": 12545.26}, {"lots": 5, "amt": 15681.57}, {"lots": 6, "amt": 18817.88}, {"lots": 7, "amt": 21954.2}, {"lots": 8, "amt": 25090.51}, {"lots": 9, "amt": 28226.82}, {"lots": 10, "amt": 31363.14}, {"lots": 12, "amt": 37635.78}, {"lots": 14, "amt": 43908.4}, {"lots": 16, "amt": 50181.02}, {"lots": 18, "amt": 56453.65}, {"lots": 20, "amt": 62726.28}, {"lots": 30, "amt": 94089.42}, {"lots": 40, "amt": 125452.56}, {"lots": 50, "amt": 156815.69}, {"lots": 60, "amt": 188178.84}, {"lots": 70, "amt": 219541.98}, {"lots": 80, "amt": 250905.11}, {"lots": 90, "amt": 282268.26}, {"lots": 100, "amt": 313631.39}, {"lots": 120, "amt": 376357.67}, {"lots": 140, "amt": 439083.95}, {"lots": 160, "amt": 501810.23}, {"lots": 180, "amt": 564536.51}, {"lots": 200, "amt": 627262.79}, {"lots": 400, "amt": 1254525.56}, {"lots": 600, "amt": 1881788.35}, {"lots": 800, "amt": 2509051.15}, {"lots": 1000, "amt": 3136313.93}, {"lots": 1200, "amt": 3763576.71}, {"lots": 1400, "amt": 4390839.5}, {"lots": 1600, "amt": 5018102.28}, {"lots": 1800, "amt": 5645365.06}, {"lots": 2000, "amt": 6272627.86}, {"lots": 4000, "amt": 12545255.7}, {"lots": 6000, "amt": 18817883.56}]}, {"code": "06880", "name": "MOMENTA-W", "type": "inst", "price": "295.60", "lot": 20, "fee": 5972, "subStart": "2026-06-29", "subEnd": "2026-07-03", "listDate": "2026-07-08", "cornerstone": "14家/50%", "cs": 6, "hot": "🔥极高", "hs": 5, "mcap": "~590亿", "gs": true, "sponsor": "中金+德银", "loc": "北京", "sh": "曹旭东16%+上汽9.5%+奔驰6.4%", "gain": "+25~45%", "dec": "重仓·甲尾", "note": "物理AI第一股·GIC+富达+BlackRock+奔驰+比亚迪基石", "pubLots": 99692, "interest": 3, "mech": "B机制", "margin": "—", "jiaTiers": [10, 30, 60, 100, 200, 300, 500, 600, 800], "yiTiers": [], "allLots": [{"lots": 1, "amt": 5971.62}, {"lots": 2, "amt": 11943.25}, {"lots": 3, "amt": 17914.87}, {"lots": 4, "amt": 23886.5}, {"lots": 5, "amt": 29858.11}, {"lots": 6, "amt": 35829.73}, {"lots": 7, "amt": 41801.36}, {"lots": 8, "amt": 47772.98}, {"lots": 9, "amt": 53744.61}, {"lots": 10, "amt": 59716.23}, {"lots": 15, "amt": 89574.33}, {"lots": 20, "amt": 119432.45}, {"lots": 25, "amt": 149290.56}, {"lots": 30, "amt": 179148.68}, {"lots": 35, "amt": 209006.79}, {"lots": 40, "amt": 238864.89}, {"lots": 45, "amt": 268723.01}, {"lots": 50, "amt": 298581.12}, {"lots": 100, "amt": 597162.25}, {"lots": 150, "amt": 895743.37}, {"lots": 200, "amt": 1194324.5}, {"lots": 250, "amt": 1492905.64}, {"lots": 300, "amt": 1791486.76}, {"lots": 350, "amt": 2090067.88}, {"lots": 400, "amt": 2388649.01}, {"lots": 450, "amt": 2687230.13}, {"lots": 500, "amt": 2985811.25}, {"lots": 1000, "amt": 5971622.52}, {"lots": 1500, "amt": 8957433.78}, {"lots": 2000, "amt": 11943245.05}, {"lots": 2500, "amt": 14929056.3}, {"lots": 3000, "amt": 17914867.55}, {"lots": 3500, "amt": 20900678.82}, {"lots": 4000, "amt": 23886490.08}, {"lots": 4500, "amt": 26872301.35}, {"lots": 5000, "amt": 29858112.6}, {"lots": 10000, "amt": 59716225.2}, {"lots": 15000, "amt": 89574337.8}, {"lots": 20000, "amt": 119432450.4}, {"lots": 25000, "amt": 149290563}, {"lots": 30000, "amt": 179148675.6}, {"lots": 35000, "amt": 209006788.2}, {"lots": 40000, "amt": 238864900.8}, {"lots": 45000, "amt": 268723013.4}]}, {"code": "07687", "name": "易控智驾", "type": "inst", "price": "81.16-87.92", "lot": 50, "fee": 4440, "subStart": "2026-06-29", "subEnd": "2026-07-03", "listDate": "2026-07-08", "cornerstone": "11家/50%", "cs": 6, "hot": "🔥极高", "hs": 5, "mcap": "~178亿", "gs": true, "sponsor": "海通国际+中信里昂", "loc": "福建上杭", "sh": "蓝水生33%+紫金4.1%+宁德4.5%", "gain": "+30~55%", "dec": "重仓·乙头", "note": "紫金基石加投+宁德D轮突击·迁址紫金总部", "pubLots": 52264, "interest": 3, "mech": "B机制", "margin": "—", "jiaTiers": [20, 40, 90, 180, 200, 400, 600, 800, 1000], "yiTiers": [], "allLots": [{"lots": 1, "amt": 4440.34}, {"lots": 2, "amt": 8880.67}, {"lots": 3, "amt": 13321.01}, {"lots": 4, "amt": 17761.33}, {"lots": 5, "amt": 22201.66}, {"lots": 6, "amt": 26642}, {"lots": 7, "amt": 31082.34}, {"lots": 8, "amt": 35522.67}, {"lots": 9, "amt": 39963.01}, {"lots": 10, "amt": 44403.34}, {"lots": 12, "amt": 53284}, {"lots": 14, "amt": 62164.67}, {"lots": 16, "amt": 71045.34}, {"lots": 18, "amt": 79926.01}, {"lots": 20, "amt": 88806.67}, {"lots": 30, "amt": 133210.01}, {"lots": 40, "amt": 177613.34}, {"lots": 50, "amt": 222016.68}, {"lots": 60, "amt": 266420.02}, {"lots": 70, "amt": 310823.36}, {"lots": 80, "amt": 355226.7}, {"lots": 90, "amt": 399630.02}, {"lots": 100, "amt": 444033.37}, {"lots": 120, "amt": 532840.03}, {"lots": 140, "amt": 621646.71}, {"lots": 160, "amt": 710453.39}, {"lots": 180, "amt": 799260.06}, {"lots": 200, "amt": 888066.73}, {"lots": 400, "amt": 1776133.47}, {"lots": 600, "amt": 2664200.2}, {"lots": 800, "amt": 3552266.93}, {"lots": 1000, "amt": 4440333.65}, {"lots": 2000, "amt": 8880667.32}, {"lots": 3000, "amt": 13321000.98}, {"lots": 4000, "amt": 17761334.65}, {"lots": 8000, "amt": 35522669.28}, {"lots": 12000, "amt": 53284003.92}, {"lots": 16000, "amt": 71045338.55}]}, {"code": "07656", "name": "瑞为技术", "type": "zhuang", "zs": 79, "price": "21.66", "lot": 200, "fee": 4376, "subStart": "2026-06-29", "subEnd": "2026-07-03", "listDate": "2026-07-08", "cornerstone": "无", "cs": 1, "hot": "🟡高", "hs": 4, "mcap": "~66亿", "gs": false, "sponsor": "华泰+建银+农银", "loc": "厦门", "sh": "詹东晖28%+英特尔4.6%", "gain": "-15~+100%+", "dec": "妖股博弈", "note": "🦄最强妖股·三无+18C·创始人婚变·暗盘必走", "pubLots": 7022, "interest": 3, "mech": "18C", "margin": "—", "jiaTiers": [20, 45, 90, 150, 250, 450, 600, 900, 1000], "yiTiers": [], "allLots": [{"lots": 1, "amt": 4375.69}, {"lots": 2, "amt": 8751.37}, {"lots": 3, "amt": 13127.06}, {"lots": 4, "amt": 17502.76}, {"lots": 5, "amt": 21878.43}, {"lots": 6, "amt": 26254.13}, {"lots": 7, "amt": 30629.82}, {"lots": 8, "amt": 35005.51}, {"lots": 9, "amt": 39381.19}, {"lots": 10, "amt": 43756.88}, {"lots": 15, "amt": 65635.32}, {"lots": 20, "amt": 87513.77}, {"lots": 25, "amt": 109392.2}, {"lots": 30, "amt": 131270.64}, {"lots": 35, "amt": 153149.09}, {"lots": 40, "amt": 175027.53}, {"lots": 45, "amt": 196905.96}, {"lots": 50, "amt": 218784.41}, {"lots": 100, "amt": 437568.83}, {"lots": 150, "amt": 656353.22}, {"lots": 200, "amt": 875137.64}, {"lots": 250, "amt": 1093922.05}, {"lots": 300, "amt": 1312706.47}, {"lots": 350, "amt": 1531490.88}, {"lots": 400, "amt": 1750275.29}, {"lots": 450, "amt": 1969059.69}, {"lots": 500, "amt": 2187844.11}, {"lots": 600, "amt": 2625412.93}, {"lots": 700, "amt": 3062981.75}, {"lots": 800, "amt": 3500550.58}, {"lots": 900, "amt": 3938119.4}, {"lots": 1000, "amt": 4375688.22}, {"lots": 1250, "amt": 5469610.28}, {"lots": 1500, "amt": 6563532.34}, {"lots": 1750, "amt": 7657454.39}, {"lots": 2000, "amt": 8751376.45}, {"lots": 2250, "amt": 9845298.5}, {"lots": 2500, "amt": 10939220.56}, {"lots": 3000, "amt": 13127064.65}]}, {"code": "09971", "name": "基本半导体", "type": "zhuang", "zs": 75, "price": "27.49-31.62", "lot": 200, "fee": 6388, "subStart": "2026-06-29", "subEnd": "2026-07-03", "listDate": "2026-07-08", "cornerstone": "无", "cs": 1, "hot": "🔥极高", "hs": 5, "mcap": "~59亿", "gs": false, "sponsor": "国金+中银", "loc": "深圳", "sh": "汪之涵46%+闻泰3.7%", "gain": "-15~+100%+", "dec": "赛道博弈", "note": "SiC极热·中信退出保荐·创始人减持·对赌", "pubLots": 6847, "interest": 3, "mech": "18C", "margin": "—", "jiaTiers": [15, 30, 50, 100, 150, 300, 450, 600, 700], "yiTiers": [], "allLots": [{"lots": 1, "amt": 6387.78}, {"lots": 2, "amt": 12775.55}, {"lots": 3, "amt": 19163.33}, {"lots": 4, "amt": 25551.11}, {"lots": 5, "amt": 31938.89}, {"lots": 6, "amt": 38326.66}, {"lots": 7, "amt": 44714.45}, {"lots": 8, "amt": 51102.23}, {"lots": 9, "amt": 57490.01}, {"lots": 10, "amt": 63877.77}, {"lots": 15, "amt": 95816.66}, {"lots": 20, "amt": 127755.55}, {"lots": 25, "amt": 159694.44}, {"lots": 30, "amt": 191633.32}, {"lots": 35, "amt": 223572.22}, {"lots": 40, "amt": 255511.1}, {"lots": 45, "amt": 287449.99}, {"lots": 50, "amt": 319388.88}, {"lots": 100, "amt": 638777.75}, {"lots": 150, "amt": 958166.63}, {"lots": 200, "amt": 1277555.51}, {"lots": 250, "amt": 1596944.39}, {"lots": 300, "amt": 1916333.26}, {"lots": 350, "amt": 2235722.14}, {"lots": 400, "amt": 2555111.01}, {"lots": 450, "amt": 2874499.9}, {"lots": 500, "amt": 3193888.76}, {"lots": 600, "amt": 3832666.52}, {"lots": 700, "amt": 4471444.27}, {"lots": 800, "amt": 5110222.03}, {"lots": 900, "amt": 5748999.79}, {"lots": 1000, "amt": 6387777.55}, {"lots": 1250, "amt": 7984721.93}, {"lots": 1500, "amt": 9581666.31}, {"lots": 1750, "amt": 11178610.7}, {"lots": 2000, "amt": 12775555.08}, {"lots": 2250, "amt": 14372499.46}, {"lots": 2500, "amt": 15969443.86}, {"lots": 2750, "amt": 17566388.24}, {"lots": 3000, "amt": 19163332.62}, {"lots": 3250, "amt": 20760277}]}, {"code": "01770", "name": "东方科脉", "type": "zhuang", "zs": 50, "price": "78.64-101.11", "lot": 50, "fee": 5107, "subStart": "2026-06-29", "subEnd": "2026-07-03", "listDate": "2026-07-08", "cornerstone": "无", "cs": 1, "hot": "🟢中", "hs": 2, "mcap": "~46亿", "gs": false, "sponsor": "中信(独保)", "loc": "嘉兴", "sh": "周爱军37%", "gain": "+5~20%", "dec": "放弃", "note": "中信独保=暗盘即巅峰·赛道不热", "pubLots": 10238, "interest": 3, "mech": "B机制", "margin": "—", "jiaTiers": [18, 30, 70, 140, 200, 400, 600, 800], "yiTiers": [], "allLots": [{"lots": 1, "amt": 5106.5}, {"lots": 2, "amt": 10212.97}, {"lots": 3, "amt": 15319.46}, {"lots": 4, "amt": 20425.94}, {"lots": 5, "amt": 25532.43}, {"lots": 6, "amt": 30638.91}, {"lots": 7, "amt": 35745.4}, {"lots": 8, "amt": 40851.88}, {"lots": 9, "amt": 45958.37}, {"lots": 10, "amt": 51064.85}, {"lots": 12, "amt": 61277.82}, {"lots": 14, "amt": 71490.79}, {"lots": 16, "amt": 81703.75}, {"lots": 18, "amt": 91916.73}, {"lots": 20, "amt": 102129.69}, {"lots": 30, "amt": 153194.54}, {"lots": 40, "amt": 204259.39}, {"lots": 50, "amt": 255324.23}, {"lots": 60, "amt": 306389.08}, {"lots": 70, "amt": 357453.92}, {"lots": 80, "amt": 408518.78}, {"lots": 90, "amt": 459583.62}, {"lots": 100, "amt": 510648.47}, {"lots": 120, "amt": 612778.17}, {"lots": 140, "amt": 714907.86}, {"lots": 160, "amt": 817037.55}, {"lots": 180, "amt": 919167.24}, {"lots": 200, "amt": 1021296.95}, {"lots": 400, "amt": 2042593.88}, {"lots": 600, "amt": 3063890.83}, {"lots": 800, "amt": 4085187.78}, {"lots": 1000, "amt": 5106484.72}, {"lots": 1200, "amt": 6127781.66}, {"lots": 1400, "amt": 7149078.61}, {"lots": 1600, "amt": 8170375.55}, {"lots": 1800, "amt": 9191672.49}, {"lots": 2000, "amt": 10212969.44}, {"lots": 3000, "amt": 15319454.16}, {"lots": 4000, "amt": 20425938.86}]}, {"code": "08090", "name": "宝盖新材", "type": "cold", "price": "6.15-8.51", "lot": 500, "fee": 4298, "subStart": "2026-06-29", "subEnd": "2026-07-03", "listDate": "2026-07-08", "cornerstone": "无", "cs": 1, "hot": "⚪冷", "hs": 0, "mcap": "~5亿", "gs": false, "sponsor": "中泰国际", "loc": "淄博", "sh": "刘振韬夫妻97%", "gain": "-30~+10%", "dec": "放弃", "note": "GEM·沟盖板·夫妻店·三死穴", "pubLots": 14470, "interest": 3, "mech": "GEM", "margin": "—", "jiaTiers": [20, 40, 90, 100, 200, 400, 600, 900, 1000], "yiTiers": [], "allLots": [{"lots": 1, "amt": 4297.91}, {"lots": 2, "amt": 8595.82}, {"lots": 3, "amt": 12893.73}, {"lots": 4, "amt": 17191.65}, {"lots": 5, "amt": 21489.55}, {"lots": 6, "amt": 25787.47}, {"lots": 7, "amt": 30085.37}, {"lots": 8, "amt": 34383.29}, {"lots": 9, "amt": 38681.2}, {"lots": 10, "amt": 42979.11}, {"lots": 12, "amt": 51574.94}, {"lots": 14, "amt": 60170.77}, {"lots": 16, "amt": 68766.59}, {"lots": 18, "amt": 77362.41}, {"lots": 20, "amt": 85958.24}, {"lots": 30, "amt": 128937.35}, {"lots": 40, "amt": 171916.48}, {"lots": 50, "amt": 214895.58}, {"lots": 60, "amt": 257874.69}, {"lots": 70, "amt": 300853.82}, {"lots": 80, "amt": 343832.93}, {"lots": 90, "amt": 386812.05}, {"lots": 100, "amt": 429791.17}, {"lots": 120, "amt": 515749.41}, {"lots": 140, "amt": 601707.63}, {"lots": 160, "amt": 687665.87}, {"lots": 180, "amt": 773624.1}, {"lots": 200, "amt": 859582.34}, {"lots": 240, "amt": 1031498.8}, {"lots": 280, "amt": 1203415.27}, {"lots": 320, "amt": 1375331.73}, {"lots": 360, "amt": 1547248.21}, {"lots": 400, "amt": 1719164.66}, {"lots": 500, "amt": 2148955.83}, {"lots": 600, "amt": 2578747}, {"lots": 700, "amt": 3008538.18}, {"lots": 800, "amt": 3438329.35}, {"lots": 1000, "amt": 4297911.68}, {"lots": 1200, "amt": 5157494.01}]}, {"code": "00537", "name": "普源精电", "type": "ah", "ahCode": "688337", "price": "≤45.98", "lot": 100, "fee": 4644, "subStart": "2026-06-30", "subEnd": "2026-07-06", "listDate": "2026-07-09", "cornerstone": "7家(高瓴HHLR+CPE)", "cs": 4, "hot": "🟡中高", "hs": 3, "mcap": "A股待查", "gs": true, "sponsor": "中信", "loc": "苏州", "sh": "高瓴+阳光电源", "gain": "+5~20%", "dec": "适度·小甲", "note": "A+H电子测量仪器龙头·高瓴基石·全球第8", "pubLots": 24802, "interest": 4, "mech": "B机制", "margin": "—", "jiaTiers": [20, 40, 80, 100, 200, 400, 600, 800, 1000], "yiTiers": [], "allLots": [{"lots": 1, "amt": 4644.37}, {"lots": 2, "amt": 9288.74}, {"lots": 3, "amt": 13933.11}, {"lots": 4, "amt": 18577.49}, {"lots": 5, "amt": 23221.85}, {"lots": 6, "amt": 27866.22}, {"lots": 7, "amt": 32510.6}, {"lots": 8, "amt": 37154.97}, {"lots": 9, "amt": 41799.34}, {"lots": 10, "amt": 46443.71}, {"lots": 15, "amt": 69665.56}, {"lots": 20, "amt": 92887.42}, {"lots": 25, "amt": 116109.26}, {"lots": 30, "amt": 139331.12}, {"lots": 35, "amt": 162552.98}, {"lots": 40, "amt": 185774.84}, {"lots": 45, "amt": 208996.69}, {"lots": 50, "amt": 232218.54}, {"lots": 60, "amt": 278662.25}, {"lots": 70, "amt": 325105.96}, {"lots": 80, "amt": 371549.66}, {"lots": 90, "amt": 417993.37}, {"lots": 100, "amt": 464437.08}, {"lots": 200, "amt": 928874.17}, {"lots": 300, "amt": 1393311.25}, {"lots": 400, "amt": 1857748.33}, {"lots": 500, "amt": 2322185.41}, {"lots": 600, "amt": 2786622.5}, {"lots": 700, "amt": 3251059.58}, {"lots": 800, "amt": 3715496.67}, {"lots": 900, "amt": 4179933.75}, {"lots": 1000, "amt": 51088079.14}, {"lots": 2000, "amt": 9288741.65}, {"lots": 3000, "amt": 13933112.49}, {"lots": 4000, "amt": 18577483.32}, {"lots": 5000, "amt": 23221854.16}, {"lots": 6000, "amt": 27866224.98}, {"lots": 7000, "amt": 32510595.81}, {"lots": 8000, "amt": 37154966.65}, {"lots": 9000, "amt": 41799337.46}]}, {"code": "01377", "name": "鼎泰高科", "type": "ah", "ahCode": "301377", "ahPrice": "¥553.80", "ahDisc": "-36%", "price": "380.00", "lot": 100, "fee": 38383, "subStart": "2026-06-30", "subEnd": "2026-07-06", "listDate": "2026-07-09", "cornerstone": "17家/43%", "cs": 3, "hot": "🟢中", "hs": 2, "mcap": "~2,278亿(A)", "gs": true, "sponsor": "中信+汇丰", "loc": "东莞", "sh": "东莞女首富", "gain": "-5~+15%", "dec": "一手摸奖", "note": "入场费3.8万极贵·A股5日跌16%·中信暗盘跑", "pubLots": 12632, "interest": 4, "mech": "B机制", "margin": "—", "jiaTiers": [2, 5, 10, 20, 30, 52, 78, 100, 109], "yiTiers": [], "allLots": [{"lots": 1, "amt": 38383}, {"lots": 2, "amt": 76766}, {"lots": 3, "amt": 115149}, {"lots": 4, "amt": 153532}, {"lots": 5, "amt": 191915}, {"lots": 6, "amt": 230298}, {"lots": 7, "amt": 268681}, {"lots": 8, "amt": 307064}, {"lots": 9, "amt": 345447}, {"lots": 10, "amt": 383830}, {"lots": 15, "amt": 575745}, {"lots": 20, "amt": 767660}, {"lots": 25, "amt": 959575}, {"lots": 30, "amt": 1151490}, {"lots": 35, "amt": 1343405}, {"lots": 40, "amt": 1535320}, {"lots": 45, "amt": 1727235}, {"lots": 50, "amt": 1919150}, {"lots": 60, "amt": 2302980}, {"lots": 70, "amt": 2686810}, {"lots": 80, "amt": 3070640}, {"lots": 90, "amt": 3454470}, {"lots": 100, "amt": 3838300}, {"lots": 200, "amt": 7676600}, {"lots": 300, "amt": 11514900}, {"lots": 400, "amt": 15353200}, {"lots": 500, "amt": 19191500}, {"lots": 600, "amt": 23029800}, {"lots": 700, "amt": 26868100}, {"lots": 800, "amt": 30706400}, {"lots": 900, "amt": 34544700}, {"lots": 1000, "amt": 38383000}, {"lots": 2000, "amt": 76766000}, {"lots": 3000, "amt": 115149000}, {"lots": 4000, "amt": 153532000}, {"lots": 5000, "amt": 191915000}]}, {"code": "02475", "name": "立讯精密", "type": "ah", "ahCode": "002475", "price": "≤63.28", "lot": 100, "fee": 6392, "subStart": "2026-06-30", "subEnd": "2026-07-06", "listDate": "2026-07-09", "cornerstone": "34家(淡马锡+GIC+高瓴)", "cs": 6, "hot": "🔥极高", "hs": 5, "mcap": "募240亿HKD", "gs": true, "sponsor": "中信+高盛+中金", "loc": "深圳", "sh": "淡马锡+GIC+ADIA+高瓴+腾讯+富达", "gain": "+10~30%", "dec": "重仓·甲尾", "note": "超级IPO·34家基石全明星·精密制造龙头", "pubLots": 383000, "interest": 4, "mech": "B机制", "margin": "—", "jiaTiers": [10, 30, 60, 100, 300, 400, 600, 700], "yiTiers": [], "allLots": [{"lots": 1, "amt": 6391.82}, {"lots": 2, "amt": 12783.64}, {"lots": 3, "amt": 19175.45}, {"lots": 4, "amt": 25567.27}, {"lots": 5, "amt": 31959.09}, {"lots": 6, "amt": 38350.92}, {"lots": 7, "amt": 44742.73}, {"lots": 8, "amt": 51134.55}, {"lots": 9, "amt": 57526.37}, {"lots": 10, "amt": 63918.18}, {"lots": 15, "amt": 95877.26}, {"lots": 20, "amt": 127836.36}, {"lots": 25, "amt": 159795.45}, {"lots": 30, "amt": 191754.54}, {"lots": 35, "amt": 223713.62}, {"lots": 40, "amt": 255672.71}, {"lots": 45, "amt": 287631.81}, {"lots": 50, "amt": 319590.89}, {"lots": 60, "amt": 383509.07}, {"lots": 70, "amt": 447427.25}, {"lots": 80, "amt": 511345.43}, {"lots": 90, "amt": 575263.61}, {"lots": 100, "amt": 639181.79}, {"lots": 200, "amt": 1278363.58}, {"lots": 300, "amt": 1917545.37}, {"lots": 400, "amt": 2556727.15}, {"lots": 500, "amt": 3195908.95}, {"lots": 600, "amt": 3835090.73}, {"lots": 700, "amt": 4474272.51}, {"lots": 800, "amt": 5113454.3}, {"lots": 900, "amt": 5752636.09}, {"lots": 1000, "amt": 6391817.88}, {"lots": 2000, "amt": 12783635.75}, {"lots": 3000, "amt": 19175453.65}, {"lots": 4000, "amt": 25567271.52}, {"lots": 5000, "amt": 31959089.4}, {"lots": 6000, "amt": 38350907.28}, {"lots": 7000, "amt": 44742725.15}, {"lots": 8000, "amt": 51134543.05}, {"lots": 9000, "amt": 57526360.92}]}, {"code": "06951", "name": "三环集团", "type": "ah", "ahCode": "300408", "price": "≤100.30", "lot": 100, "fee": 10131, "subStart": "2026-06-30", "subEnd": "2026-07-06", "listDate": "2026-07-09", "cornerstone": "17家/50%(淡马锡+阿里+腾讯)", "cs": 6, "hot": "🔥极高", "hs": 5, "mcap": "~2,703亿(A)", "gs": true, "sponsor": "中国银河国际", "loc": "潮州", "sh": "张万镇(潮州首富)", "gain": "+10~25%", "dec": "重仓·甲尾", "note": "MLCC龙头·淡马锡+阿里+腾讯基石·供货比亚迪/特斯拉/英伟达", "pubLots": 71364, "interest": 4, "mech": "B机制", "margin": "—", "jiaTiers": [9, 15, 35, 70, 100, 200, 300, 400], "yiTiers": [], "allLots": [{"lots": 1, "amt": 10131.16}, {"lots": 2, "amt": 20262.3}, {"lots": 3, "amt": 30393.46}, {"lots": 4, "amt": 40524.61}, {"lots": 5, "amt": 50655.76}, {"lots": 6, "amt": 60786.91}, {"lots": 7, "amt": 70918.08}, {"lots": 8, "amt": 81049.22}, {"lots": 9, "amt": 91180.38}, {"lots": 10, "amt": 101311.53}, {"lots": 15, "amt": 151967.29}, {"lots": 20, "amt": 202623.05}, {"lots": 25, "amt": 253278.82}, {"lots": 30, "amt": 303934.57}, {"lots": 35, "amt": 354590.34}, {"lots": 40, "amt": 405246.1}, {"lots": 45, "amt": 455901.87}, {"lots": 50, "amt": 506557.62}, {"lots": 60, "amt": 607869.15}, {"lots": 70, "amt": 709180.68}, {"lots": 80, "amt": 810492.2}, {"lots": 90, "amt": 911803.72}, {"lots": 100, "amt": 1013115.25}, {"lots": 200, "amt": 2026230.51}, {"lots": 300, "amt": 3039345.76}, {"lots": 400, "amt": 4052461.02}, {"lots": 500, "amt": 5065576.28}, {"lots": 1000, "amt": 10131152.56}, {"lots": 1500, "amt": 15196728.83}, {"lots": 2000, "amt": 20262305.1}, {"lots": 2500, "amt": 25327881.38}, {"lots": 5000, "amt": 50655762.76}, {"lots": 7500, "amt": 75983644.13}]}, {"code": "02797", "name": "齐云山食品", "type": "cold", "price": "5.00-8.00", "lot": 500, "fee": 4040, "subStart": "2026-06-30", "subEnd": "2026-07-06", "listDate": "2026-07-09", "cornerstone": "无", "cs": 1, "hot": "⚪冷", "hs": 1, "mcap": "微盘", "gs": false, "sponsor": "中泰国际", "loc": "江西", "sh": "创始人控股", "gain": "-10~+10%", "dec": "放弃", "note": "南酸枣糕·无基石·2025营收利润双降", "pubLots": 5000, "interest": 4, "mech": "B机制", "margin": "—", "jiaTiers": [20, 40, 90, 100, 200, 400, 700, 900, 1000], "yiTiers": [], "allLots": [{"lots": 1, "amt": 4040.35}, {"lots": 2, "amt": 8080.68}, {"lots": 3, "amt": 12121.02}, {"lots": 4, "amt": 16161.35}, {"lots": 5, "amt": 20201.7}, {"lots": 6, "amt": 24242.05}, {"lots": 7, "amt": 28282.38}, {"lots": 8, "amt": 32322.72}, {"lots": 9, "amt": 36363.05}, {"lots": 10, "amt": 40403.4}, {"lots": 15, "amt": 60605.1}, {"lots": 20, "amt": 80806.8}, {"lots": 25, "amt": 101008.5}, {"lots": 30, "amt": 121210.2}, {"lots": 35, "amt": 141411.9}, {"lots": 40, "amt": 161613.6}, {"lots": 45, "amt": 181815.3}, {"lots": 50, "amt": 202017}, {"lots": 60, "amt": 242420.4}, {"lots": 70, "amt": 282823.8}, {"lots": 80, "amt": 323227.2}, {"lots": 90, "amt": 363630.6}, {"lots": 100, "amt": 404034}, {"lots": 200, "amt": 808068}, {"lots": 300, "amt": 1212102}, {"lots": 400, "amt": 1616136}, {"lots": 500, "amt": 2020170}, {"lots": 600, "amt": 2424204}, {"lots": 700, "amt": 2828238}, {"lots": 800, "amt": 3232272}, {"lots": 900, "amt": 3636306}, {"lots": 1000, "amt": 4040340}, {"lots": 1500, "amt": 6060510}]}, {"code": "03752", "name": "珞石机器人", "type": "inst", "price": "38.00", "lot": 100, "fee": 3838, "subStart": "2026-06-30", "subEnd": "2026-07-06", "listDate": "2026-07-09", "cornerstone": "5家/31%", "cs": 3, "hot": "🟡中高", "hs": 3, "mcap": "待确认", "gs": true, "sponsor": "中金+国泰君安", "loc": "北京", "sh": "庹华39%+国家制造业基金9.7%", "gain": "+10~30%", "dec": "适度·小甲", "note": "柔性协作机器人第一·具身智能·资金可复用", "pubLots": 23032, "interest": 4, "mech": "B机制", "margin": "—", "jiaTiers": [20, 50, 100, 200, 300, 500, 700, 1000], "yiTiers": [], "allLots": [{"lots": 1, "amt": 3838.32}, {"lots": 2, "amt": 7676.65}, {"lots": 3, "amt": 11514.97}, {"lots": 4, "amt": 15353.29}, {"lots": 5, "amt": 19191.61}, {"lots": 6, "amt": 23029.94}, {"lots": 7, "amt": 26868.26}, {"lots": 8, "amt": 30706.59}, {"lots": 9, "amt": 34544.9}, {"lots": 10, "amt": 38383.24}, {"lots": 15, "amt": 57574.85}, {"lots": 20, "amt": 76766.45}, {"lots": 25, "amt": 95958.08}, {"lots": 30, "amt": 115149.69}, {"lots": 35, "amt": 134341.3}, {"lots": 40, "amt": 153532.92}, {"lots": 45, "amt": 172724.54}, {"lots": 50, "amt": 191916.16}, {"lots": 60, "amt": 230299.38}, {"lots": 70, "amt": 268682.61}, {"lots": 80, "amt": 307065.85}, {"lots": 90, "amt": 345449.06}, {"lots": 100, "amt": 383832.3}, {"lots": 200, "amt": 767664.6}, {"lots": 300, "amt": 1151496.9}, {"lots": 400, "amt": 1535329.2}, {"lots": 500, "amt": 1919161.5}, {"lots": 600, "amt": 2302993.8}, {"lots": 700, "amt": 2686826.1}, {"lots": 800, "amt": 3070658.4}, {"lots": 900, "amt": 3454490.7}, {"lots": 1000, "amt": 3838323}, {"lots": 2000, "amt": 7676646}, {"lots": 3000, "amt": 11514969}, {"lots": 4000, "amt": 15353292}, {"lots": 5000, "amt": 19191615}, {"lots": 6000, "amt": 23029938}, {"lots": 7000, "amt": 26868261}, {"lots": 8000, "amt": 30706584}, {"lots": 9000, "amt": 34544907}]}, {"code": "02249", "name": "晶合集成", "type": "ah", "ahCode": "688249", "ahPrice": "¥59.26", "ahDisc": "-51%", "price": "30.00-32.30", "lot": 100, "fee": 3263, "subStart": "2026-06-30", "subEnd": "2026-07-07", "listDate": "2026-07-10", "cornerstone": "20家/52%", "cs": 4, "hot": "🟡热", "hs": 3, "mcap": "~1,190亿(A)", "gs": true, "sponsor": "中金", "loc": "合肥", "sh": "合肥国资", "gain": "+5~20%", "dec": "适度·小甲", "note": "A+H·H折让51%·半导体晶圆代工·A股强势", "pubLots": 216167, "interest": 5, "mech": "B机制", "margin": "—", "jiaTiers": [30, 60, 100, 200, 300, 600, 900, 1000], "yiTiers": [], "allLots": [{"lots": 1, "amt": 3262.57}, {"lots": 2, "amt": 6525.14}, {"lots": 3, "amt": 9787.72}, {"lots": 4, "amt": 13050.3}, {"lots": 5, "amt": 16312.87}, {"lots": 6, "amt": 19575.44}, {"lots": 7, "amt": 22838.02}, {"lots": 8, "amt": 26100.6}, {"lots": 9, "amt": 29363.16}, {"lots": 10, "amt": 32625.74}, {"lots": 20, "amt": 65251.49}, {"lots": 30, "amt": 97877.24}, {"lots": 40, "amt": 130502.98}, {"lots": 50, "amt": 163128.72}, {"lots": 60, "amt": 195754.47}, {"lots": 70, "amt": 228380.21}, {"lots": 80, "amt": 261005.97}, {"lots": 90, "amt": 293631.71}, {"lots": 100, "amt": 326257.45}, {"lots": 200, "amt": 652514.91}, {"lots": 300, "amt": 978772.36}, {"lots": 400, "amt": 1305029.82}, {"lots": 500, "amt": 1631287.28}, {"lots": 600, "amt": 1957544.74}, {"lots": 700, "amt": 2283802.19}, {"lots": 800, "amt": 2610059.65}, {"lots": 900, "amt": 2936317.1}, {"lots": 1000, "amt": 3262574.56}, {"lots": 2000, "amt": 6525149.1}, {"lots": 3000, "amt": 9787723.66}, {"lots": 4000, "amt": 13050298.2}, {"lots": 5000, "amt": 16312872.76}]}, {"code": "06745", "name": "滨化股份", "type": "ah", "ahCode": "601678", "ahPrice": "¥6.47", "ahDisc": "-52%", "price": "3.05-3.59", "lot": 1000, "fee": 3626, "subStart": "2026-06-30", "subEnd": "2026-07-07", "listDate": "2026-07-10", "cornerstone": "7家/35%", "cs": 2, "hot": "⚪低", "hs": 1, "mcap": "~133亿(A)", "gs": true, "sponsor": "华泰+建银", "loc": "滨州", "sh": "滨化集团", "gain": "-5~+10%", "dec": "一手/放弃", "note": "A+H·H折让52%但化工赛道冷", "pubLots": 35200, "interest": 5, "mech": "B机制", "margin": "—", "jiaTiers": [20, 50, 100, 200, 300, 500, 800, 1000], "yiTiers": [], "allLots": [{"lots": 1, "amt": 3626.21}, {"lots": 2, "amt": 7252.41}, {"lots": 3, "amt": 10878.62}, {"lots": 4, "amt": 14504.82}, {"lots": 5, "amt": 18131.02}, {"lots": 6, "amt": 21757.23}, {"lots": 7, "amt": 25383.44}, {"lots": 8, "amt": 29009.64}, {"lots": 9, "amt": 32635.85}, {"lots": 10, "amt": 36262.05}, {"lots": 15, "amt": 54393.07}, {"lots": 20, "amt": 72524.11}, {"lots": 25, "amt": 90655.12}, {"lots": 30, "amt": 108786.16}, {"lots": 35, "amt": 126917.18}, {"lots": 40, "amt": 145048.21}, {"lots": 45, "amt": 163179.23}, {"lots": 50, "amt": 181310.26}, {"lots": 60, "amt": 217572.31}, {"lots": 70, "amt": 253834.37}, {"lots": 80, "amt": 290096.41}, {"lots": 90, "amt": 326358.46}, {"lots": 100, "amt": 362620.51}, {"lots": 200, "amt": 725241.04}, {"lots": 300, "amt": 1087861.55}, {"lots": 400, "amt": 1450482.05}, {"lots": 500, "amt": 1813102.58}]}, {"code": "02523", "name": "永康控股", "type": "cold", "price": "2.20-2.68", "lot": 2000, "fee": 5414, "subStart": "2026-06-30", "subEnd": "2026-07-08", "listDate": "2026-07-13", "cornerstone": "无", "cs": 1, "hot": "⚪冷", "hs": 0, "mcap": "极微", "gs": false, "sponsor": "华富建业+同人融资", "loc": "新加坡", "sh": "Navis+创始人", "gain": "-20~+5%", "dec": "放弃", "note": "集装箱堆场·无基石·冷门", "pubLots": 25800, "interest": 6, "mech": "B机制", "margin": "—", "jiaTiers": [10, 30, 70, 100, 200, 300, 500, 700, 900], "yiTiers": [], "allLots": [{"lots": 1, "amt": 5414.05}, {"lots": 2, "amt": 10828.12}, {"lots": 3, "amt": 16242.16}, {"lots": 4, "amt": 21656.22}, {"lots": 5, "amt": 27070.27}, {"lots": 6, "amt": 32484.34}, {"lots": 7, "amt": 37898.39}, {"lots": 8, "amt": 43312.44}, {"lots": 9, "amt": 48726.5}, {"lots": 10, "amt": 54140.56}, {"lots": 15, "amt": 81210.83}, {"lots": 20, "amt": 108281.11}, {"lots": 25, "amt": 135351.39}, {"lots": 30, "amt": 162421.67}, {"lots": 35, "amt": 189491.95}, {"lots": 40, "amt": 216562.22}, {"lots": 45, "amt": 243632.5}, {"lots": 50, "amt": 270702.78}, {"lots": 100, "amt": 541405.55}, {"lots": 150, "amt": 812108.35}, {"lots": 200, "amt": 1082811.12}, {"lots": 250, "amt": 1353513.9}, {"lots": 300, "amt": 1624216.68}, {"lots": 350, "amt": 1894919.45}, {"lots": 400, "amt": 2165622.25}, {"lots": 450, "amt": 2436325.02}]}]